pandora_cli-0.1.0.dist-info/entry_points.txt
pandora_cli-0.1.0.dist-info/WHEEL
pandora_cli-0.1.0.dist-info/top_level.txt
pandora_cli-0.1.0.dist-info/METADATA
pandora_cli-0.1.0.dist-info/RECORD
pandora_cli-0.1.0.dist-info/metadata.json
pandora_cli-0.1.0.dist-info/DESCRIPTION.rst
pandora_cli/cli.py
pandora_cli/__init__.py
pandora_cli/api.py
pandora_cli/downloader.py
