Metadata-Version: 2.0
Name: pandora-cli
Version: 0.1.0
Summary: CLI wrapper for pandora.com
Home-page: https://github.com/t-8ch/pandora-cli
Author: Thomas Weißschuh
Author-email: pandora-cli@t-8ch.de
License: GPL3
Keywords: pandora.com pandora cli download music stream
Platform: UNKNOWN
Requires-Dist: requests
Requires-Dist: cryptography
Requires-Dist: click
Requires-Dist: mutagen
